setup.py
RTI_lab58_face/__init__.py
RTI_lab58_face/main.py
RTI_lab58_face.egg-info/PKG-INFO
RTI_lab58_face.egg-info/SOURCES.txt
RTI_lab58_face.egg-info/dependency_links.txt
RTI_lab58_face.egg-info/entry_points.txt
RTI_lab58_face.egg-info/requires.txt
RTI_lab58_face.egg-info/top_level.txt
RTI_lab58_face/basemodels/ArcFace.py
RTI_lab58_face/basemodels/Boosting.py
RTI_lab58_face/basemodels/DeepID.py
RTI_lab58_face/basemodels/DlibResNet.py
RTI_lab58_face/basemodels/DlibWrapper.py
RTI_lab58_face/basemodels/Facenet.py
RTI_lab58_face/basemodels/Facenet512.py
RTI_lab58_face/basemodels/FbDeepFace.py
RTI_lab58_face/basemodels/OpenFace.py
RTI_lab58_face/basemodels/SFaceWrapper.py
RTI_lab58_face/basemodels/VGGFace.py
RTI_lab58_face/basemodels/__init__.py
RTI_lab58_face/commons/__init__.py
RTI_lab58_face/commons/distance.py
RTI_lab58_face/commons/functions.py
RTI_lab58_face/commons/realtime.py
RTI_lab58_face/detectors/DlibWrapper.py
RTI_lab58_face/detectors/FaceDetector.py
RTI_lab58_face/detectors/MediapipeWrapper.py
RTI_lab58_face/detectors/MtcnnWrapper.py
RTI_lab58_face/detectors/OpenCvWrapper.py
RTI_lab58_face/detectors/RetinaFaceWrapper.py
RTI_lab58_face/detectors/SsdWrapper.py
RTI_lab58_face/detectors/__init__.py
RTI_lab58_face/extendedmodels/Age.py
RTI_lab58_face/extendedmodels/Emotion.py
RTI_lab58_face/extendedmodels/Gender.py
RTI_lab58_face/extendedmodels/Race.py
RTI_lab58_face/extendedmodels/__init__.py
RTI_lab58_face/models/__init__.py