Metadata-Version: 2.1
Name: RTI-lab58-face
Version: 0.0.2
Summary: Art
Home-page: UNKNOWN
Author: INF
Author-email: rnsbhargav@gmail.com
License: UNKNOWN
Platform: UNKNOWN
Classifier: Programming Language :: Python :: 3
Classifier: Operating System :: OS Independent
Requires-Python: >=3.5.5
